poetry_plugin_lambda_build/__init__.py
poetry_plugin_lambda_build/commands.py
poetry_plugin_lambda_build/docker.py
poetry_plugin_lambda_build/parameters.py
poetry_plugin_lambda_build/plugin.py
poetry_plugin_lambda_build/recipes.py
poetry_plugin_lambda_build/requirements.py
poetry_plugin_lambda_build/utils.py
poetry_plugin_lambda_build/walker.py
poetry_plugin_lambda_build/zip.py
poetry_plugin_lambda_build-2.1.1.dist-info/LICENSE
poetry_plugin_lambda_build-2.1.1.dist-info/METADATA
poetry_plugin_lambda_build-2.1.1.dist-info/WHEEL
poetry_plugin_lambda_build-2.1.1.dist-info/entry_points.txt
poetry_plugin_lambda_build-2.1.1.dist-info/RECORD
