Metadata-Version: 2.3
Name: poetry-plugin-lambda-build
Version: 2.1.1
Summary: The plugin for poetry that allows you to build zip packages suited for serverless deployment like AWS Lambda, Google App Engine, Azure App Service, and more...
Author: Michal Murawski
Author-email: mmurawski777@gmail.com
Requires-Python: >=3.9,<4.0
Classifier: Programming Language :: Python :: 3
Classifier: Programming Language :: Python :: 3.9
Classifier: Programming Language :: Python :: 3.10
Classifier: Programming Language :: Python :: 3.11
Classifier: Programming Language :: Python :: 3.12
Classifier: Programming Language :: Python :: 3.13
Requires-Dist: docker (>=7.1.0,<8.0.0)
